{
  "welcome_new_user": "ุฃููุงู ุจู! ุฏุนูุง ููู ุจุฅุนุฏุงุฏ ูููู ุงูุดุฎุตู. ุงูุฑุฌุงุก ุงุฎุชูุงุฑ ูุบุชู ุงูููุถูุฉ:",
  "welcome_existing_user": "ุฃููุงู ุจุนูุฏุชูุ {name}!",
  "choose_language": "ุงูุฑุฌุงุก ุงุฎุชูุงุฑ ูุบุชู ุงูููุถูุฉ:",
  "invalid_language": " ุงุฎุชูุงุฑ ุบูุฑ ุตุญูุญ. ุงูุฑุฌุงุก ุงุฎุชูุงุฑ ูุบุชู ุงูููุถูุฉ:",
  "choose_gender": "ุงูุฑุฌุงุก ุงุฎุชูุงุฑ ุฌูุณู:",
  "male": "ุฐูุฑ",
  "female": "ุฃูุซู",
  "other": "ุขุฎุฑ",
  "choose_region": "ุงูุฑุฌุงุก ุงุฎุชูุงุฑ ููุทูุชู:",
  "invalid_region": "ุงูููุทูุฉ ุงููุฎุชุงุฑุฉ ุบูุฑ ุตุงูุญุฉ. ุงูุฑุฌุงุก ุงูุงุฎุชูุงุฑ ูู ุงููุงุฆูุฉ.",
  "choose_country_in_region": "ุงูุฑุฌุงุก ุงุฎุชูุงุฑ ุจูุฏู ูู {region}:",
  "country_not_found_in_region": "ูู ูุชู ุงูุนุซูุฑ ุนูู ุงูุจูุฏ ูู ุงูููุทูุฉ ุงููุญุฏุฏุฉ. ุงูุฑุฌุงุก ุงูุงุฎุชูุงุฑ ูู ุงููุงุฆูุฉ ุฃู ูุชุงุจุฉ ุงูุงุณู ุงููุงูู ุจุนูุงูุฉ.",
  "profile_complete": "ุดูุฑุงู ูู! ุงูุชูู ูููู ุงูุดุฎุตู.",
  "profile_updated": "ุชู ุชุญุฏูุซ ูููู ุงูุดุฎุตู.",
  "cancel_profile": "ุชู ุฅูุบุงุก ุฅูุดุงุก ุงูููู ุงูุดุฎุตู.",
  "forward_message_admin_info": "ุฑุณุงูุฉ ูู {user_name} (ุงููุนุฑู: {user_id}):",
  "payment_prompt": "ูุชูุนูู ููุฒุฉ ุงูุจุญุซ ุงููุชูุฏู ุนู ุดุฑููุ ูุฑุฌู ุงูุฏูุน ุฅูู ุฃุญุฏ ุงูุญุณุงุจุงุช ุงูุชุงููุฉ:\\\\\\\\\\nPayeer: {payeer_account}\\\\\\\\\\nBitcoin: {bitcoin_address}\\\\\\\\\\nุจุนุฏ ุงูุฏูุนุ ูุฑุฌู ุงูุถุบุท ุนูู ุงูุฒุฑ ุฃุฏูุงู ูุฅุฑุณุงู ูุนุฑู ุงููุนุงููุฉ ุฃู ููุทุฉ ุดุงุดุฉ ุฅูู ุงููุณุคูู ููุชุญูู.",
  "payment_received_pending_verification": "ุชู ุงุณุชูุงู ูุนูููุงุช ุงูุฏูุน ุงูุฎุงุตุฉ ุจู ููู ููุฏ ุงูุชุญูู ูู ูุจู ุงููุณุคูู. ุณูุชู ุฅุนูุงูู ุจูุฌุฑุฏ ุชูุนูู ุงูููุฒุฉ.",
  "feature_activated": "ุชู ุชูุนูู ููุฒุฉ ุงูุจุญุซ ุงููุชูุฏู ุนู ุดุฑูู ูุญุณุงุจู!",
  "search_partner_prompt_language": "ูุฑุฌู ุงุฎุชูุงุฑ ูุบุฉ ุงูุดุฑูู:",
  "search_partner_prompt_gender": "ูุง ูู ุฌูุณ ุงูุดุฑูู ุงูุฐู ุชุจุญุซ ุนููุ",
  "search_partner_prompt_country": "ูุง ูู ุจูุฏ ุงูุดุฑูู ุงูุฐู ุชุจุญุซ ุนููุ (ุงูุชุจ ุงุณู ุงูููุทูุฉ ุฃููุงูุ ุฃู 'ุฃู ุจูุฏ')",
  "search_results_none": "ูู ูุชู ุงูุนุซูุฑ ุนูู ุดุฑูุงุก ูุชุงุญูู ุญุงููุงู.",
  "search_results_found": "ุชู ุงูุนุซูุฑ ุนูู {count} ุดุฑูู ูุญุชูู:",
  "admin_user_blocked": "ุชู ุญุธุฑ ุงููุณุชุฎุฏู {user_id}.",
  "admin_user_unblocked": "ุชู ูู ุญุธุฑ ุงููุณุชุฎุฏู {user_id}.",
  "admin_payment_verified": "ุชู ุงูุชุญูู ูู ุงูุฏูุน ูููุณุชุฎุฏู {user_id}. ุชู ุชูุนูู ุงูููุฒุฉ.",
  "admin_error_user_not_found": "ุฎุทุฃ: ูู ูุชู ุงูุนุซูุฑ ุนูู ุงููุณุชุฎุฏู {user_id}.",
  "error_generic": "ุญุฏุซ ุฎุทุฃ. ูุฑุฌู ุงููุญุงููุฉ ูุฑุฉ ุฃุฎุฑู ูุงุญููุง.",
  "feature_already_activated": "ูุฏูู ุจุงููุนู ุงูููุฒุฉ ุงููููุฒุฉ ููุนูุฉ.",
  "payment_verify_button": "ููุฏ ููุช ุจุงูุฏูุน - ุชุญูู ุงูุขู",
  "payment_send_proof": "ูุฑุฌู ุฅุฑุณุงู ูุนุฑู ุงููุนุงููุฉ ุงูุฎุงุต ุจูุ ุฃู ููุทุฉ ุดุงุดุฉ ููุฏูุนุ ุฃู ุฃู ุฅุซุจุงุช ุฏูุน ุขุฎุฑ ุงูุขู. ุณูููู ุงููุณุคูู ุจูุฑุงุฌุนุชู ูุฑูุจูุง.",
  "payment_received_pending_verification": "ุชู ุงุณุชูุงู ูุนูููุงุช ุงูุฏูุน ุงูุฎุงุตุฉ ุจู ููู ููุฏ ุงูุชุญูู ูู ูุจู ุงููุณุคูู. ุณูุชู ุฅุนูุงูู ุจูุฌุฑุฏ ุชูุนูู ุงูููุฒุฉ.",
  "payment_rejected": "ููุฃุณูุ ูู ูุชู ุงูุชุญูู ูู ุฏูุนุชู ูู ูุฐุง ุงูููุช. ูุฑุฌู ุงูุงุชุตุงู ุจุงูุฏุนู ุฃู ุงููุญุงููุฉ ูุฑุฉ ุฃุฎุฑู.",
  "profile_incomplete": "ูุฑุฌู ุฅููุงู ูููู ุงูุดุฎุตู ูุจู ุงูุจุญุซ ุนู ุดุฑูุงุก.",
  "language": "ุงููุบุฉ",
  "gender": "ุงูุฌูุณ",
  "country": "ุงูุจูุฏ",
  "any_gender": "ุฃู ุฌูุณ",
  "any_country": "ุฃู ุจูุฏ",
  "invalid_gender": "ุงูุฌูุณ ุงููุฎุชุงุฑ ุบูุฑ ุตุงูุญ. ุงูุฑุฌุงุก ุงูุงุฎุชูุงุฑ ูู ุงููุงุฆูุฉ.",
  "payment_send_proof_reminder": "ูุฑุฌู ุฅุฑุณุงู ูุนุฑู ุงููุนุงููุฉ ุฃู ููุทุฉ ุดุงุดุฉ ูุฏููู ุนูู ุงูุฏูุน.",
  "search_partner_prompt_region_for_country": "ุฃููุงูุ ุงุฎุชุฑ ููุทูุฉ ุจูุฏ ุงูุดุฑููุ ุฃู ุงุฎุชุฑ 'ุฃู ุจูุฏ'.",
  "search_partner_select_country_from_region": "ุงูุขูุ ูุฑุฌู ุงุฎุชูุงุฑ ุจูุฏ ุงูุดุฑูู ูู {region}ุ ุฃู ุงูุชุจ 'ุฃู ุจูุฏ' ุฅุฐุง ุงุฎุชุฑุช ุชูู ุงูููุทูุฉ.",
  "welcome_message": "ูุฑุญุจูุง ุจู ูู ุงูุจูุช!",
  "language_changed": "ุชู ุชุบููุฑ ูุบุชู ุฅูู ุงูุนุฑุจูุฉ.",
  "any_language": "ุฃู ูุบุฉ",
  "cancel": "ุฅูุบุงุก",
  "update_country": "ุชุญุฏูุซ ุงูุจูุฏ",
  "country_updated": "โ ุชู ุชุญุฏูุซ ุงูุจูุฏ.",
  "update_gender": "ุชุญุฏูุซ ุงูุฌูุณ",
  "menu_payment": "๐ณ ุงูุฏูุน",
  "update_region": "ุชุญุฏูุซ ุงูููุทูุฉ",
  "current_profile": "ูููู ุงูุดุฎุตู ุงูุญุงูู",
  "main_menu_text": "๐ ุงููุงุฆูุฉ ุงูุฑุฆูุณูุฉ - ุงูุฑุฌุงุก ุงุฎุชูุงุฑ ุฎูุงุฑ:",
  "menu_settings": "โ๏ธ ุงูุฅุนุฏุงุฏุงุช",
  "select_field_to_update": "ุงุฎุชุฑ ุญููุงู ูุชุญุฏูุซู:",
  "menu_profile": "๐ค ุงูููู ุงูุดุฎุตู",
  "gender_updated": "โ ุชู ุชุญุฏูุซ ุงูุฌูุณ.",
  "back": "ุฑุฌูุน",
  "region_updated": "โ ุชู ุชุญุฏูุซ ุงูููุทูุฉ.",
  "language_updated": "โ ุชู ุชุญุฏูุซ ุงููุบุฉ.",
  "menu_search": "๐ ุจุญุซ",
  "menu_premium_features": "โญ ููุฒุงุช ุจุฑููููู",
  "menu_hidden": "โ ุงููุงุฆูุฉ ูุฎููุฉ.",
  "menu_help": "โ ูุณุงุนุฏุฉ",
  "update_language": "ุชุญุฏูุซ ุงููุบุฉ",
  "contact_accepted_confirmation": "ุชู ูุจูู ุทูุจ ุงูุงุชุตุงู.",
  "region": "ุงูููุทูุฉ",
  "premium_feature_2": "ููุฒุฉ ุจุฑููููู 2",
  "disabled": "ูุนุทู",
  "help_search": "ูุณุงุนุฏุฉ ุงูุจุญุซ",
  "any_region": "ุฃู ููุทูุฉ",
  "enable_notifications": "ุชูุนูู ุงูุฅุดุนุงุฑุงุช",
  "premium_feature_1": "ููุฒุฉ ุจุฑููููู 1",
  "profile_commands": "ุฃูุงูุฑ ุงูููู ุงูุดุฎุตู",
  "search_commands": "ุฃูุงูุฑ ุงูุจุญุซ",
  "basic_commands": "ุงูุฃูุงูุฑ ุงูุฃุณุงุณูุฉ",
  "admin_payments": "ูุฏููุนุงุช ุงููุดุฑู",
  "admin_users": "ูุณุชุฎุฏูู ุงููุดุฑู",
  "help_title": "ุนููุงู ุงููุณุงุนุฏุฉ",
  "premium_features_footer": "ุชุฐููู ููุฒุงุช ุจุฑููููู",
  "contact_request_sent": "ุชู ุฅุฑุณุงู ุทูุจ ุงูุงุชุตุงู.",
  "update_profile": "ุชุญุฏูุซ ุงูููู ุงูุดุฎุตู",
  "help_cancel": "ูุณุงุนุฏุฉ ุงูุฅูุบุงุก",
  "accept_contact": "ูุจูู ุงูุงุชุตุงู",
  "settings_commands": "ุฃูุงูุฑ ุงูุฅุนุฏุงุฏุงุช",
  "premium_features_title": "ุนููุงู ููุฒุงุช ุจุฑููููู",
  "admin_broadcast": "ุจุซ ุงููุดุฑู",
  "admin_settings": "ุฅุนุฏุงุฏุงุช ุงููุดุฑู",
  "redirecting_to_profile": "ุฅุนุงุฏุฉ ุงูุชูุฌูู ุฅูู ุงูููู ุงูุดุฎุตู",
  "contact_request": "ุทูุจ ุงุชุตุงู",
  "more_results": "ุงููุฒูุฏ ูู ุงููุชุงุฆุฌ",
  "help_help": "ูุณุงุนุฏุฉ ุงููุณุงุนุฏุฉ",
  "search_again": "ุจุญุซ ูุฑุฉ ุฃุฎุฑู",
  "contact": "ุงุชุตุงู",
  "help_profile": "ูุณุงุนุฏุฉ ุงูููู ุงูุดุฎุตู",
  "decline_contact": "ุฑูุถ ุงูุงุชุตุงู",
  "premium_feature_4": "ููุฒุฉ ุจุฑููููู 4",
  "contact_accepted": "ุชู ูุจูู ุงูุงุชุตุงู",
  "help_menu": "ูุณุงุนุฏุฉ ุงููุงุฆูุฉ",
  "notifications_disabled": "ุชู ุชุนุทูู ุงูุฅุดุนุงุฑุงุช",
  "contact_declined_confirmation": "ุชู ุชุฃููุฏ ุฑูุถ ุงูุงุชุตุงู.",
  "help_settings": "ูุณุงุนุฏุฉ ุงูุฅุนุฏุงุฏุงุช",
  "enabled": "ููุนู",
  "settings_title": "ุนููุงู ุงูุฅุนุฏุงุฏุงุช",
  "admin_stats": "ุฅุญุตุงุฆูุงุช ุงููุดุฑู",
  "payment_commands": "ุฃูุงูุฑ ุงูุฏูุน",
  "admin_status": "ุญุงูุฉ ุงููุดุฑู",
  "contact_declined": "ุชู ุฑูุถ ุงูุงุชุตุงู",
  "no_username": "ูุง ููุฌุฏ ุงุณู ูุณุชุฎุฏู",
  "disable_notifications": "ุชุนุทูู ุงูุฅุดุนุงุฑุงุช",
  "help_start": "ูุณุงุนุฏุฉ ุงูุจุฏุก",
  "premium_feature_3": "ููุฒุฉ ุจุฑููููู 3",
  "user_not_found": "ุงููุณุชุฎุฏู ุบูุฑ ููุฌูุฏ",
  "help_additional_info": "ูุนูููุงุช ูุณุงุนุฏุฉ ุฅุถุงููุฉ",
  "starting_new_search": "ุจุฏุก ุจุญุซ ุฌุฏูุฏ",
  "change_language": "ุชุบููุฑ ุงููุบุฉ",
  "notifications_enabled": "ุชู ุชูุนูู ุงูุฅุดุนุงุฑุงุช",
  "notifications": "ุงูุฅุดุนุงุฑุงุช",
  "help_payment": "ูุณุงุนุฏุฉ ุงูุฏูุน"
}

